creart-0.3.0.dist-info/METADATA
creart-0.3.0.dist-info/WHEEL
creart-0.3.0.dist-info/entry_points.txt
creart-0.3.0.dist-info/licenses/LICENSE
creart/__init__.py
creart/builtins/__init__.py
creart/builtins/loop.py
creart/creator.py
creart/py.typed
creart-0.3.0.dist-info/RECORD
