Metadata-Version: 2.1
Name: creart
Version: 0.3.0
Summary: a universal, extensible class instantiation helper
Author-Email: GreyElaina <GreyElaina@outlook.com>
License: MIT
Requires-Python: >=3.8
Requires-Dist: importlib-metadata>=3.6
